{"Runs": [{"status": "incomplete", "expID": 3, "channel": 2, "user": "WhittinghamA", "labID": "NRC", "material_info": "Na", "Techniques": [{"params": {"rest_time_T": 30, "record_every_dT": 0.5, "record_every_dE": 0.1, "E_range": "E_RANGE_5V"}, "TechID": "OCV"}, {"params": {"vs_initial": true, "vs_final": true, "initial_voltage_step": 0, "final_voltage_step": 0, "frequency_number": 32, "duration_step": 5, "amplitude": 0.01, "final_frequency": 1, "initial_frequency": 200000, "step_number": 0, "record_every_dT": 0.1, "record_every_dI": 0.1, "sweep": false, "average_n_times": 2, "correction": false, "wait_for_steady": 0.1, "I_range": "I_RANGE_1mA", "E_range": "E_RANGE_AUTO", "bandwidth": "BW_5"}, "TechID": "PEIS"}, {"params": {"vs_initial": [false, false, false, false, false], "voltage_step": [0, -1, 0, 0, 0], "scan_rate": [0.025, 0.025, 0.025, 0.025, 0.025], "record_every_dE": 0.005, "begin_measuring_I": 0.2, "n_cycles": 2, "scan_number": 2, "average_every_dE": false, "end_measuring_I": 1, "I_range": "I_RANGE_1mA", "E_range": "E_RANGE_2_5V", "bandwidth": "BW_5"}, "TechID": "CV"}, {"params": {"vs_initial": [false, false, false, false, false], "voltage_step": [0, -0.2, 0, 0, 0], "scan_rate": [0.025, 0.025, 0.025, 0.025, 0.025], "record_every_dE": 0.005, "begin_measuring_I": 0.2, "n_cycles": 3, "scan_number": 2, "average_every_dE": false, "end_measuring_I": 1, "I_range": "I_RANGE_1mA", "E_range": "E_RANGE_2_5V", "bandwidth": "BW_5"}, "TechID": "CV"}, {"params": {"vs_initial": [false, false, false, false, false], "voltage_step": [0, -0.2, 0, 0, 0], "scan_rate": [0.05, 0.05, 0.05, 0.05, 0.05], "record_every_dE": 0.005, "begin_measuring_I": 0.2, "n_cycles": 3, "scan_number": 2, "average_every_dE": false, "end_measuring_I": 1, "I_range": "I_RANGE_1mA", "E_range": "E_RANGE_2_5V", "bandwidth": "BW_5"}, "TechID": "CV"}, {"params": {"vs_initial": [false, false, false, false, false], "voltage_step": [0, -0.2, 0, 0, 0], "scan_rate": [0.075, 0.075, 0.075, 0.075, 0.075], "record_every_dE": 0.005, "begin_measuring_I": 0.5, "n_cycles": 1, "scan_number": 2, "average_every_dE": true, "end_measuring_I": 1, "I_range": "I_RANGE_1mA", "E_range": "E_RANGE_2_5V", "bandwidth": "BW_5"}, "TechID": "CV"}, {"params": {"vs_initial": [false, false, false, false, false], "voltage_step": [0, -0.2, 0, 0, 0], "scan_rate": [0.1, 0.1, 0.1, 0.1, 0.1], "record_every_dE": 0.005, "begin_measuring_I": 0.2, "n_cycles": 3, "scan_number": 2, "average_every_dE": false, "end_measuring_I": 1, "I_range": "I_RANGE_1mA", "E_range": "E_RANGE_2_5V", "bandwidth": "BW_5"}, "TechID": "CV"}, {"params": {"vs_initial": [false, false, false, false, false], "voltage_step": [0, -0.2, 0, 0, 0], "scan_rate": [0.125, 0.125, 0.125, 0.125, 0.125], "record_every_dE": 0.005, "begin_measuring_I": 0.2, "n_cycles": 3, "scan_number": 2, "average_every_dE": false, "end_measuring_I": 1, "I_range": "I_RANGE_1mA", "E_range": "E_RANGE_2_5V", "bandwidth": "BW_5"}, "TechID": "CV"}, {"params": {"vs_initial": [false, false, false, false, false], "voltage_step": [0, -0.2, 0, 0, 0], "scan_rate": [0.15, 0.15, 0.15, 0.15, 0.15], "record_every_dE": 0.005, "begin_measuring_I": 0.2, "n_cycles": 3, "scan_number": 2, "average_every_dE": false, "end_measuring_I": 1, "I_range": "I_RANGE_1mA", "E_range": "E_RANGE_2_5V", "bandwidth": "BW_5"}, "TechID": "CV"}, {"params": {"vs_initial": true, "vs_final": true, "initial_voltage_step": 0, "final_voltage_step": 0, "frequency_number": 32, "duration_step": 5, "amplitude": 0.01, "final_frequency": 1, "initial_frequency": 200000, "step_number": 0, "record_every_dT": 0.1, "record_every_dI": 0.1, "sweep": false, "average_n_times": 2, "correction": false, "wait_for_steady": 0.1, "I_range": "I_RANGE_1mA", "E_range": "E_RANGE_AUTO", "bandwidth": "BW_5"}, "TechID": "PEIS"}, {"params": {"vs_initial": [false], "voltage_step": [-1.8], "duration_step": [300], "n_cycles": 0, "record_every_di": 0.05, "record_every_dt": 0.05, "I_range": "I_RANGE_AUTO", "E_range": "E_RANGE_AUTO", "bandwidth": "BW_5"}, "TechID": "CA"}]}]}